{
  "contractVersion": "tasq.lifecycle-certification.v1",
  "status": "published-release-certified",
  "productShape": "tasq-local",
  "supportedTargets": ["darwin-arm64", "linux-x64-gnu"],
  "releaseAssets": {
    "archive": "tasq-v<version>-<target>.tar.gz",
    "installer": "tasq-v<version>-<target>.install.ts",
    "manifest": "tasq-v<version>-<target>.release.json",
    "checksums": "tasq-v<version>-<target>.SHA256SUMS",
    "sbom": "tasq-v<version>-<target>.cdx.json",
    "attestationAuthority": "protected-github-actions-tag-workflow"
  },
  "installation": {
    "layout": "side-by-side-explicit-prefix",
    "versionDirectory": "<prefix>/lib/tasq/<version>/<target>",
    "activeExecutable": "<prefix>/bin/tasq",
    "installRecord": "<prefix>/share/tasq/installations/<version>-<target>.json",
    "activation": "atomic-managed-symlink",
    "shellStartupMutation": false,
    "implicitGlobalIdentityMutation": false
  },
  "data": {
    "locationAuthority": "TASQ_HOME-or-user-config",
    "managedByInstaller": false,
    "uninstallDisposition": "preserved-not-touched",
    "rollback": "restore-matching-verified-snapshot-and-activate-matching-binary",
    "downgradeInPlace": false
  },
  "authority": {
    "undocumentedListener": false,
    "listenerOnInstall": false,
    "credentialReadOnInstall": false,
    "deviceClockReadOnInstall": false,
    "runtimeAuthorityTime": "injected-clock-with-explicit-systemClock-composition-adapter"
  },
  "candidateEvidence": {
    "test": "packages/tasq-cli/test/public-lifecycle.test.ts",
    "requiredCiTargets": ["verify (macos-14)", "verify (ubuntu-latest)"],
    "journey": [
      "verify-release-envelope",
      "install-outside-checkout",
      "autonomous-onboard",
      "two-agent-contention-and-recovery",
      "inspect-same-ledger-through-console",
      "prove-foreground-console-listener-identity",
      "backup",
      "direct-upgrade",
      "inspect-same-ledger-through-upgraded-console",
      "doctor-and-read-after-upgrade",
      "restore-snapshot-with-matching-binary",
      "uninstall-all-binaries-with-data-preserved"
    ],
    "negativeCases": [
      "tampered-archive-refused",
      "installer-checksum-mismatch-refused",
      "wrong-host-target-refused",
      "unmanaged-binary-collision-refused",
      "different-bytes-same-version-refused"
    ]
  },
  "publishedArtifactEvidence": {
    "status": "passed",
    "release": "https://github.com/gwendall/tasq/releases/tag/v0.3.0",
    "sourceCommit": "c093ed58ab2a9e38dbd9d877ba75021997761057",
    "certifiedAt": "2026-07-23T22:50:40Z",
    "workflowRun": "https://github.com/gwendall/tasq/actions/runs/30051196124",
    "certificationSourceCommit": "d5b77df0ec51578409929ee23c83ef7aa02c4069",
    "registryTarballsMatched": true,
    "targets": {
      "darwin-arm64": {
        "status": "passed",
        "job": "https://github.com/gwendall/tasq/actions/runs/30051196124/job/89353439684"
      },
      "linux-x64-gnu": {
        "status": "passed",
        "job": "https://github.com/gwendall/tasq/actions/runs/30051196124/job/89353439711"
      }
    },
    "verified": [
      "every-published-asset-attestation",
      "clean-room-lifecycle-from-downloaded-assets-on-both-targets",
      "format-5-to-format-26-published-binary-migration",
      "same-ledger-installed-console",
      "public-adoption-path",
      "published-package-interactive-runtime"
    ]
  },
  "tq604Complete": true
}
